django_static_swagger_ui/.DS_Store
django_static_swagger_ui/__init__.py
django_static_swagger_ui/admin.py
django_static_swagger_ui/apps.py
django_static_swagger_ui/models.py
django_static_swagger_ui/tests.py
django_static_swagger_ui/views.py
django_static_swagger_ui/migrations/__init__.py
django_static_swagger_ui/static/.DS_Store
django_static_swagger_ui/static/swagger-ui/.DS_Store
django_static_swagger_ui/static/swagger-ui/favicon-16x16.png
django_static_swagger_ui/static/swagger-ui/favicon-32x32.png
django_static_swagger_ui/static/swagger-ui/index.css
django_static_swagger_ui/static/swagger-ui/index.html
django_static_swagger_ui/static/swagger-ui/oauth2-redirect.html
django_static_swagger_ui/static/swagger-ui/swagger-initializer.js
django_static_swagger_ui/static/swagger-ui/swagger-ui-bundle.js
django_static_swagger_ui/static/swagger-ui/swagger-ui-bundle.js.map
django_static_swagger_ui/static/swagger-ui/swagger-ui-es-bundle-core.js
django_static_swagger_ui/static/swagger-ui/swagger-ui-es-bundle-core.js.map
django_static_swagger_ui/static/swagger-ui/swagger-ui-es-bundle.js
django_static_swagger_ui/static/swagger-ui/swagger-ui-es-bundle.js.map
django_static_swagger_ui/static/swagger-ui/swagger-ui-standalone-preset.js
django_static_swagger_ui/static/swagger-ui/swagger-ui-standalone-preset.js.map
django_static_swagger_ui/static/swagger-ui/swagger-ui.css
django_static_swagger_ui/static/swagger-ui/swagger-ui.css.map
django_static_swagger_ui/static/swagger-ui/swagger-ui.js
django_static_swagger_ui/static/swagger-ui/swagger-ui.js.map
django_static_swagger_ui-5.17.14.1.dist-info/licenses/LICENSE
django_static_swagger_ui-5.17.14.1.dist-info/METADATA
django_static_swagger_ui-5.17.14.1.dist-info/WHEEL
django_static_swagger_ui-5.17.14.1.dist-info/top_level.txt
django_static_swagger_ui-5.17.14.1.dist-info/RECORD
